LICENSE
MANIFEST.in
README.md
README.rst
RELNOTES.md
setup.cfg
setup.py
tests.py
basho_erlastic.egg-info/PKG-INFO
basho_erlastic.egg-info/SOURCES.txt
basho_erlastic.egg-info/dependency_links.txt
basho_erlastic.egg-info/requires.txt
basho_erlastic.egg-info/top_level.txt
erlastic/__init__.py
erlastic/codec.py
erlastic/compat.py
erlastic/constants.py
erlastic/types.py