Metadata-Version: 1.1
Name: basho-erlastic
Version: 2.1.1
Summary: Erlastic
Home-page: http://github.com/basho/python-erlastic
Author: Samuel Stauffer, Basho Technologies
Author-email: clients@basho.com
License: UNKNOWN
Platform: UNKNOWN
Classifier: Intended Audience :: Developers
Classifier: License :: OSI Approved :: BSD License
Classifier: Operating System :: OS Independent
Classifier: Programming Language :: Python
Classifier: Topic :: Software Development :: Libraries :: Python Modules
Requires: six
